{
  "B0F4BJJNX2": {
    "first_seen": "2026-04-26",
    "prices": [
      {
        "p": 1989.99,
        "d": "2026-04-26"
      }
    ]
  },
  "B0DYLFFG79": {
    "first_seen": "2026-04-26",
    "prices": [
      {
        "p": 129.9,
        "d": "2026-04-26"
      }
    ]
  },
  "B07C7LRP6L": {
    "first_seen": "2026-04-26",
    "prices": [
      {
        "p": 308.0,
        "d": "2026-04-26"
      }
    ]
  },
  "B07BHW19H6": {
    "first_seen": "2026-04-26",
    "prices": [
      {
        "p": 383.06,
        "d": "2026-04-26"
      }
    ]
  },
  "B0BRNR7GS2": {
    "first_seen": "2026-04-26",
    "prices": [
      {
        "p": 25.85,
        "d": "2026-04-26"
      }
    ]
  },
  "B0BRNQ9BKB": {
    "first_seen": "2026-04-26",
    "prices": [
      {
        "p": 13.32,
        "d": "2026-04-26"
      }
    ]
  },
  "B0BRQNZKCC": {
    "first_seen": "2026-04-26",
    "prices": [
      {
        "p": 12.0,
        "d": "2026-04-26"
      }
    ]
  },
  "B0BRNR23LR": {
    "first_seen": "2026-04-26",
    "prices": [
      {
        "p": 13.22,
        "d": "2026-04-26"
      }
    ]
  },
  "B0BRNMHJCW": {
    "first_seen": "2026-04-26",
    "prices": [
      {
        "p": 12.98,
        "d": "2026-04-26"
      }
    ]
  },
  "B0C87WK67Z": {
    "first_seen": "2026-04-26",
    "prices": [
      {
        "p": 250.05,
        "d": "2026-04-26"
      }
    ]
  },
  "B0CMJB52D6": {
    "first_seen": "2026-04-26",
    "prices": [
      {
        "p": 524.55,
        "d": "2026-04-26"
      }
    ]
  },
  "B0CZBCRC3S": {
    "first_seen": "2026-04-26",
    "prices": []
  },
  "B0D856FJ1J": {
    "first_seen": "2026-04-26",
    "prices": [
      {
        "p": 447.11,
        "d": "2026-04-26"
      }
    ]
  },
  "B09YBXXVLQ": {
    "first_seen": "2026-04-26",
    "prices": [
      {
        "p": 357.29,
        "d": "2026-04-26"
      }
    ]
  },
  "B0BNSVWWDR": {
    "first_seen": "2026-04-26",
    "prices": [
      {
        "p": 89.0,
        "d": "2026-04-26"
      }
    ]
  },
  "B0B23B7ZCF": {
    "first_seen": "2026-04-26",
    "prices": [
      {
        "p": 37.8,
        "d": "2026-04-26"
      }
    ]
  },
  "B08YKC39Y7": {
    "first_seen": "2026-04-26",
    "prices": [
      {
        "p": 1689.0,
        "d": "2026-04-26"
      }
    ]
  },
  "B0DR8VCDCH": {
    "first_seen": "2026-04-26",
    "prices": []
  },
  "B0FDLM1L2R": {
    "first_seen": "2026-04-26",
    "prices": []
  },
  "B08TQGGTCC": {
    "first_seen": "2026-04-26",
    "prices": [
      {
        "p": 99.34,
        "d": "2026-04-26"
      }
    ]
  },
  "B0CX1G833P": {
    "first_seen": "2026-04-26",
    "prices": [
      {
        "p": 944.61,
        "d": "2026-04-26"
      }
    ]
  },
  "B09BJLFRYR": {
    "first_seen": "2026-04-26",
    "prices": []
  },
  "B09QCW73S5": {
    "first_seen": "2026-04-26",
    "prices": [
      {
        "p": 279.9,
        "d": "2026-04-26"
      }
    ]
  },
  "B0F13NWL4C": {
    "first_seen": "2026-04-26",
    "prices": [
      {
        "p": 667.18,
        "d": "2026-04-26"
      }
    ]
  },
  "B0F7Y45353": {
    "first_seen": "2026-04-26",
    "prices": [
      {
        "p": 397.17,
        "d": "2026-04-26"
      }
    ]
  },
  "B0DR9H2CXP": {
    "first_seen": "2026-04-26",
    "prices": [
      {
        "p": 674.78,
        "d": "2026-04-26"
      }
    ]
  },
  "B0BNLN6791": {
    "first_seen": "2026-04-26",
    "prices": [
      {
        "p": 268.28,
        "d": "2026-04-26"
      }
    ]
  },
  "B077MZ2MPW": {
    "first_seen": "2026-04-26",
    "prices": [
      {
        "p": 371.16,
        "d": "2026-04-26"
      }
    ]
  },
  "B0CZBCPF53": {
    "first_seen": "2026-04-26",
    "prices": []
  },
  "B07F4J9MFZ": {
    "first_seen": "2026-04-26",
    "prices": [
      {
        "p": 149.9,
        "d": "2026-04-26"
      }
    ]
  },
  "B0D54PNXRN": {
    "first_seen": "2026-04-26",
    "prices": [
      {
        "p": 146.91,
        "d": "2026-04-26"
      }
    ]
  },
  "B0DKPF8LSF": {
    "first_seen": "2026-04-26",
    "prices": [
      {
        "p": 573.04,
        "d": "2026-04-26"
      }
    ]
  },
  "B09T5JC5Z1": {
    "first_seen": "2026-04-26",
    "prices": [
      {
        "p": 572.36,
        "d": "2026-04-26"
      }
    ]
  },
  "B0D6BY5JMP": {
    "first_seen": "2026-04-26",
    "prices": [
      {
        "p": 309.9,
        "d": "2026-04-26"
      }
    ]
  },
  "B0DJ57N1WS": {
    "first_seen": "2026-04-26",
    "prices": [
      {
        "p": 149.0,
        "d": "2026-04-26"
      }
    ]
  },
  "B0B4TYHQD5": {
    "first_seen": "2026-04-26",
    "prices": [
      {
        "p": 83.9,
        "d": "2026-04-26"
      }
    ]
  },
  "B0BBGGRGDL": {
    "first_seen": "2026-04-26",
    "prices": [
      {
        "p": 223.75,
        "d": "2026-04-26"
      }
    ]
  },
  "B0BBV29JXX": {
    "first_seen": "2026-04-26",
    "prices": [
      {
        "p": 1015.99,
        "d": "2026-04-26"
      }
    ]
  },
  "B01MUHP51S": {
    "first_seen": "2026-04-26",
    "prices": [
      {
        "p": 651.51,
        "d": "2026-04-26"
      }
    ]
  },
  "B0CGY9Q4ZW": {
    "first_seen": "2026-04-26",
    "prices": [
      {
        "p": 89.98,
        "d": "2026-04-26"
      }
    ]
  }
}